MANIFEST.in
README.md
setup.cfg
setup.py
langcodes/__init__.py
langcodes/db.py
langcodes/load_subtags.py
langcodes/profiled.py
langcodes/registry_parser.py
langcodes/tag_parser.py
langcodes/util.py
langcodes/wiktionary_language_list.py
langcodes/data/aliases.csv
langcodes/data/bibliographic_codes.csv
langcodes/data/language-subtag-registry.txt
langcodes/data/subtags-1.2.db
langcodes/data/subtags-prev.db
langcodes/data/subtags.db
langcodes/data/wiktionary-languages.txt
langcodes/data/cldr/README
langcodes/data/cldr/unicode-license.txt
langcodes/data/cldr/main/ar/languages.json
langcodes/data/cldr/main/ar/listPatterns.json
langcodes/data/cldr/main/ar/scripts.json
langcodes/data/cldr/main/ar/territories.json
langcodes/data/cldr/main/ar/variants.json
langcodes/data/cldr/main/ca/languages.json
langcodes/data/cldr/main/ca/listPatterns.json
langcodes/data/cldr/main/ca/scripts.json
langcodes/data/cldr/main/ca/territories.json
langcodes/data/cldr/main/ca/variants.json
langcodes/data/cldr/main/cs/languages.json
langcodes/data/cldr/main/cs/listPatterns.json
langcodes/data/cldr/main/cs/scripts.json
langcodes/data/cldr/main/cs/territories.json
langcodes/data/cldr/main/cs/variants.json
langcodes/data/cldr/main/da/languages.json
langcodes/data/cldr/main/da/listPatterns.json
langcodes/data/cldr/main/da/scripts.json
langcodes/data/cldr/main/da/territories.json
langcodes/data/cldr/main/da/variants.json
langcodes/data/cldr/main/de/languages.json
langcodes/data/cldr/main/de/listPatterns.json
langcodes/data/cldr/main/de/scripts.json
langcodes/data/cldr/main/de/territories.json
langcodes/data/cldr/main/de/variants.json
langcodes/data/cldr/main/el/languages.json
langcodes/data/cldr/main/el/listPatterns.json
langcodes/data/cldr/main/el/scripts.json
langcodes/data/cldr/main/el/territories.json
langcodes/data/cldr/main/el/variants.json
langcodes/data/cldr/main/en/languages.json
langcodes/data/cldr/main/en/listPatterns.json
langcodes/data/cldr/main/en/scripts.json
langcodes_py2.egg-info/PKG-INFO
langcodes_py2.egg-info/SOURCES.txt
langcodes_py2.egg-info/dependency_links.txt
langcodes_py2.egg-info/not-zip-safe
langcodes_py2.egg-info/top_level.txt