Metadata-Version: 1.1
Name: langcodes-py2
Version: 1.2.0
Summary: Labels and compares human languages in a standardized way -- Python 2 backport
Home-page: http://github.com/LuminosoInsight/langcodes
Author: Luminoso Technologies, Inc.
Author-email: rspeer@luminoso.com
License: MIT
Platform: any
Classifier: Programming Language :: Python :: 2
Classifier: Programming Language :: Python :: 2.7
Classifier: Programming Language :: Python :: 3
Classifier: Programming Language :: Python :: 3.3
Classifier: Programming Language :: Python :: 3.4
Classifier: Programming Language :: Python :: 3.5
Classifier: License :: OSI Approved :: MIT License
Classifier: Operating System :: OS Independent
Classifier: Topic :: Software Development :: Libraries :: Python Modules
